<annotation>
	<folder>my-project-name</folder>
	<filename>n03126707_4684.JPEG</filename>
	<path>/my-project-name/n03126707_4684.JPEG</path>
	<source>
		<database>Unspecified</database>
	</source>
	<size>
		<width>500</width>
		<height>339</height>
		<depth>3</depth>
	</size>
	<object>
		<name>crane</name>
		<pose>Unspecified</pose>
		<truncated>0</truncated>
		<difficult>0</difficult>
		<bndbox>
			<xmin>85</xmin>
			<ymin>180</ymin>
			<xmax>297</xmax>
			<ymax>279</ymax>
		</bndbox>
	</object>
</annotation>